<?xml version="1.0" encoding="utf-8" ?><dwsync><file name="2003Butte007web.jpg" server="uofr.net/hiattzhao/" local="3379610252" remote="318763443841637147" Dst="-1" /><file name="2003Cleveland013copyweb.jpg" server="uofr.net/hiattzhao/" local="3383566904" remote="318763443841637148" Dst="-1" /><file name="2003DowntownLA002web.jpg" server="uofr.net/hiattzhao/" local="3383839941" remote="318763443841637150" Dst="-1" /><file name="2003DowntownLA005web.jpg" server="uofr.net/hiattzhao/" local="3383839942" remote="318763443841637151" Dst="-1" /><file name="2003DowntownLA008web.jpg" server="uofr.net/hiattzhao/" local="3379610255" remote="318763443841637153" Dst="-1" /><file name="2003NewOrleans331web.jpg" server="uofr.net/hiattzhao/" local="3408900502" remote="318763443841637154" Dst="-1" /><file name="2003Portland117web.jpg" server="uofr.net/hiattzhao/" local="3384209113" remote="318763443841637156" Dst="-1" /><file name="2006PhillyCenterCity018web.jpg" server="uofr.net/hiattzhao/" local="3386530242" remote="318763443841637158" Dst="-1" /><file name="2006PhillyCenterCity075web.jpg" server="uofr.net/hiattzhao/" local="3386530275" remote="318763443841637159" Dst="-1" /><file name="2012Shanghai0620web.jpg" server="uofr.net/hiattzhao/" local="3425120194" remote="318763443841637160" Dst="-1" /><file name="2012Shanghai0828web.jpg" server="uofr.net/hiattzhao/" local="3425120196" remote="318763443841637161" Dst="-1" /><file name="2012Shanghai0932web.jpg" server="uofr.net/hiattzhao/" local="3425120198" remote="318763443841637163" Dst="-1" /><file name="2012Shanghai0939web.jpg" server="uofr.net/hiattzhao/" local="3425120200" remote="318763443841637164" Dst="-1" /><file name="2012Shanghai1706web.jpg" server="uofr.net/hiattzhao/" local="3425120202" remote="318763443841637166" Dst="-1" /><file name="2012Shanghai1711web.jpg" server="uofr.net/hiattzhao/" local="3425120204" remote="318763443841637167" Dst="-1" /><file name="2012Shanghai1714web.jpg" server="uofr.net/hiattzhao/" local="3425120206" remote="318763443841637169" Dst="-1" /><file name="2012Shanghai1715web.jpg" server="uofr.net/hiattzhao/" local="3425120208" remote="318763443841637170" Dst="-1" /><file name="2012Shanghai1723web.jpg" server="uofr.net/hiattzhao/" local="3425120210" remote="318763443841637171" Dst="-1" /><file name="2012Shanghai1729web.jpg" server="uofr.net/hiattzhao/" local="3425120212" remote="318763443841637172" Dst="-1" /><file name="2012Shanghai1731web.jpg" server="uofr.net/hiattzhao/" local="3425120214" remote="318763443841637174" Dst="-1" /><file name="2012Shanghai1733web.jpg" server="uofr.net/hiattzhao/" local="3425120216" remote="318763443841637175" Dst="-1" /><file name="2012Shanghai1740web.jpg" server="uofr.net/hiattzhao/" local="3425120217" remote="318763443841637176" Dst="-1" /><file name="2012Shanghai1744web.jpg" server="uofr.net/hiattzhao/" local="3425120219" remote="318763443841637177" Dst="-1" /><file name="2012Shanghai1827web.jpg" server="uofr.net/hiattzhao/" local="3425120221" remote="318763443841637179" Dst="-1" /></dwsync>